{
  "project_info": {
    "project_number": "196979651016",
    "project_id": "chat-app-ac105",
    "storage_bucket": "chat-app-ac105.appspot.com"
  },
  "client": [
    {
      "client_info": {
        "mobilesdk_app_id": "1:196979651016:android:668191aefcee34ce1850fd",
        "android_client_info": {
          "package_name": "com.example.chat"
        }
      },
      "oauth_client": [],
      "api_key": [
        {
          "current_key": "AIzaSyAk9e7ePTZjl3uvq4DR536BSKeCoPX9b2s"
        }
      ],
      "services": {
        "appinvite_service": {
          "other_platform_oauth_client": []
        }
      }
    }
  ],
  "configuration_version": "1"
}